mistletoe/__init__.py
mistletoe/__main__.py
mistletoe/ast_renderer.py
mistletoe/base_renderer.py
mistletoe/block_token.py
mistletoe/block_tokenizer.py
mistletoe/cli.py
mistletoe/core_tokens.py
mistletoe/html_renderer.py
mistletoe/latex_renderer.py
mistletoe/latex_token.py
mistletoe/markdown_renderer.py
mistletoe/py.typed
mistletoe/span_token.py
mistletoe/span_tokenizer.py
mistletoe/token.py
mistletoe/utils.py
mistletoe/contrib/__init__.py
mistletoe/contrib/github_wiki.py
mistletoe/contrib/jira_renderer.py
mistletoe/contrib/mathjax.py
mistletoe/contrib/md2jira.py
mistletoe/contrib/pygments_renderer.py
mistletoe/contrib/scheme.py
mistletoe/contrib/toc_renderer.py
mistletoe/contrib/xwiki20_renderer.py
mistletoe-1.5.0.dist-info/licenses/LICENSE
mistletoe-1.5.0.dist-info/METADATA
mistletoe-1.5.0.dist-info/WHEEL
mistletoe-1.5.0.dist-info/entry_points.txt
mistletoe-1.5.0.dist-info/top_level.txt
mistletoe-1.5.0.dist-info/RECORD
